{
  "took": 1861,
  "timed_out": false,
  "_shards": {
    "total": 45,
    "successful": 44,
    "skipped": 0,
    "failed": 0
  },
  "hits": {
    "total": {
      "value": 1361,
      "relation": "eq"
    },
    "max_score": null,
    "hits": []
  },
  "aggregations": {
    "2": {
      "buckets": [
        {
          "5": {
            "value": 0.3000999987125397
          },
          "6": {
            "value": 0.8194000124931335
          },
          "key_as_string": "2020-12-20T13:58:00.000+09:00",
          "key": 1608440280000,
          "doc_count": 45
        },
        {
          "5": {
            "value": 0.30000001192092896
          },
          "6": {
            "value": 0.8192999958992004
          },
          "key_as_string": "2020-12-20T13:58:30.000+09:00",
          "key": 1608440310000,
          "doc_count": 46
        },
        {
          "5": {
            "value": 0.3000999987125397
          },
          "6": {
            "value": 0.8195000290870667
          },
          "key_as_string": "2020-12-20T13:59:00.000+09:00",
          "key": 1608440340000,
          "doc_count": 45
        },
        {
          "5": {
            "value": 0.3001999855041504
          },
          "6": {
            "value": 0.8195000290870667
          },
          "key_as_string": "2020-12-20T13:59:30.000+09:00",
          "key": 1608440370000,
          "doc_count": 47
        },
        {
          "5": {
            "value": 0.3000999987125397
          },
          "6": {
            "value": 0.8195000290870667
          },
          "key_as_string": "2020-12-20T14:00:00.000+09:00",
          "key": 1608440400000,
          "doc_count": 45
        },
        {
          "5": {
            "value": 0.3001999855041504
          },
          "6": {
            "value": 0.8195000290870667
          },
          "key_as_string": "2020-12-20T14:00:30.000+09:00",
          "key": 1608440430000,
          "doc_count": 45
        },
        {
          "5": {
            "value": 0.3001999855041504
          },
          "6": {
            "value": 0.819599986076355
          },
          "key_as_string": "2020-12-20T14:01:00.000+09:00",
          "key": 1608440460000,
          "doc_count": 45
        },
        {
          "5": {
            "value": 0.3001999855041504
          },
          "6": {
            "value": 0.819599986076355
          },
          "key_as_string": "2020-12-20T14:01:30.000+09:00",
          "key": 1608440490000,
          "doc_count": 46
        },
        {
          "5": {
            "value": 0.3001999855041504
          },
          "6": {
            "value": 0.819599986076355
          },
          "key_as_string": "2020-12-20T14:02:00.000+09:00",
          "key": 1608440520000,
          "doc_count": 45
        },
        {
          "5": {
            "value": 0.3001999855041504
          },
          "6": {
            "value": 0.8197000026702881
          },
          "key_as_string": "2020-12-20T14:02:30.000+09:00",
          "key": 1608440550000,
          "doc_count": 46
        },
        {
          "5": {
            "value": 0.3001999855041504
          },
          "6": {
            "value": 0.8197000026702881
          },
          "key_as_string": "2020-12-20T14:03:00.000+09:00",
          "key": 1608440580000,
          "doc_count": 45
        },
        {
          "5": {
            "value": 0.3001999855041504
          },
          "6": {
            "value": 0.8197000026702881
          },
          "key_as_string": "2020-12-20T14:03:30.000+09:00",
          "key": 1608440610000,
          "doc_count": 46
        },
        {
          "5": {
            "value": 0.3003000020980835
          },
          "6": {
            "value": 0.8198000192642212
          },
          "key_as_string": "2020-12-20T14:04:00.000+09:00",
          "key": 1608440640000,
          "doc_count": 45
        },
        {
          "5": {
            "value": 0.3001999855041504
          },
          "6": {
            "value": 0.8198000192642212
          },
          "key_as_string": "2020-12-20T14:04:30.000+09:00",
          "key": 1608440670000,
          "doc_count": 45
        },
        {
          "5": {
            "value": 0.3001999855041504
          },
          "6": {
            "value": 0.8198000192642212
          },
          "key_as_string": "2020-12-20T14:05:00.000+09:00",
          "key": 1608440700000,
          "doc_count": 45
        },
        {
          "5": {
            "value": 0.3001999855041504
          },
          "6": {
            "value": 0.8198000192642212
          },
          "key_as_string": "2020-12-20T14:05:30.000+09:00",
          "key": 1608440730000,
          "doc_count": 46
        },
        {
          "5": {
            "value": 0.3001999855041504
          },
          "6": {
            "value": 0.8198000192642212
          },
          "key_as_string": "2020-12-20T14:06:00.000+09:00",
          "key": 1608440760000,
          "doc_count": 44
        },
        {
          "5": {
            "value": 0.3001999855041504
          },
          "6": {
            "value": 0.8198000192642212
          },
          "key_as_string": "2020-12-20T14:06:30.000+09:00",
          "key": 1608440790000,
          "doc_count": 48
        },
        {
          "5": {
            "value": 0.3001999855041504
          },
          "6": {
            "value": 0.8198000192642212
          },
          "key_as_string": "2020-12-20T14:07:00.000+09:00",
          "key": 1608440820000,
          "doc_count": 46
        },
        {
          "5": {
            "value": 0.3001999855041504
          },
          "6": {
            "value": 0.8198999762535095
          },
          "key_as_string": "2020-12-20T14:07:30.000+09:00",
          "key": 1608440850000,
          "doc_count": 43
        },
        {
          "5": {
            "value": 0.3000999987125397
          },
          "6": {
            "value": 0.8198000192642212
          },
          "key_as_string": "2020-12-20T14:08:00.000+09:00",
          "key": 1608440880000,
          "doc_count": 45
        },
        {
          "5": {
            "value": 0.3000999987125397
          },
          "6": {
            "value": 0.8198999762535095
          },
          "key_as_string": "2020-12-20T14:08:30.000+09:00",
          "key": 1608440910000,
          "doc_count": 46
        },
        {
          "5": {
            "value": 0.3001999855041504
          },
          "6": {
            "value": 0.8198999762535095
          },
          "key_as_string": "2020-12-20T14:09:00.000+09:00",
          "key": 1608440940000,
          "doc_count": 44
        },
        {
          "5": {
            "value": 0.3001999855041504
          },
          "6": {
            "value": 0.8199999928474426
          },
          "key_as_string": "2020-12-20T14:09:30.000+09:00",
          "key": 1608440970000,
          "doc_count": 45
        },
        {
          "5": {
            "value": 0.3001999855041504
          },
          "6": {
            "value": 0.8199999928474426
          },
          "key_as_string": "2020-12-20T14:10:00.000+09:00",
          "key": 1608441000000,
          "doc_count": 45
        },
        {
          "5": {
            "value": 0.3001999855041504
          },
          "6": {
            "value": 0.8199999928474426
          },
          "key_as_string": "2020-12-20T14:10:30.000+09:00",
          "key": 1608441030000,
          "doc_count": 46
        },
        {
          "5": {
            "value": 0.3001999855041504
          },
          "6": {
            "value": 0.8199999928474426
          },
          "key_as_string": "2020-12-20T14:11:00.000+09:00",
          "key": 1608441060000,
          "doc_count": 45
        },
        {
          "5": {
            "value": 0.3000999987125397
          },
          "6": {
            "value": 0.8198999762535095
          },
          "key_as_string": "2020-12-20T14:11:30.000+09:00",
          "key": 1608441090000,
          "doc_count": 46
        },
        {
          "5": {
            "value": 0.3000999987125397
          },
          "6": {
            "value": 0.8198999762535095
          },
          "key_as_string": "2020-12-20T14:12:00.000+09:00",
          "key": 1608441120000,
          "doc_count": 45
        },
        {
          "5": {
            "value": 0.3000999987125397
          },
          "6": {
            "value": 0.8198999762535095
          },
          "key_as_string": "2020-12-20T14:12:30.000+09:00",
          "key": 1608441150000,
          "doc_count": 46
        }
      ]
    }
  }
}